setup.py
RandoDraw/RandoDraw.py
RandoDraw/__init__.py
RandoDraw.egg-info/PKG-INFO
RandoDraw.egg-info/SOURCES.txt
RandoDraw.egg-info/dependency_links.txt
RandoDraw.egg-info/not-zip-safe
RandoDraw.egg-info/top_level.txt