Metadata-Version: 1.0
Name: RandoDraw
Version: 0.11
Summary: Random number guesses
Home-page: UNKNOWN
Author: Omar Eltouny
Author-email: omartouny78@gmail.com
License: UNKNOWN
Platform: UNKNOWN
